{
	"careerPostseason": {
		"appearances": 0,
		"atBats": 0,
		"basesOnBalls": 0,
		"battingAverage": 0,
		"caughtStealing": 0,
		"doublesHit": 0,
		"groundIntoDoublePlays": 0,
		"hits": 0,
		"homeRunsHit": 0,
		"onBasePercentage": 0,
		"onBasePlusSlugging": 0,
		"plateAppearances": 0,
		"runsBattedIn": 0,
		"runsScored": 0,
		"sacrificeBunts": 0,
		"sacrificeFlies": 0,
		"sluggingPercentage": 0,
		"stolenBases": 0,
		"strikeouts": 0,
		"team": null,
		"teamName": null,
		"totalBases": 0,
		"triplesHit": 0
	},
	"careerSeason": {
		"appearances": 160,
		"atBats": 597,
		"basesOnBalls": 27,
		"battingAverage": 0.25125628140703515,
		"caughtStealing": 6,
		"doublesHit": 8,
		"groundIntoDoublePlays": 2,
		"hits": 150,
		"homeRunsHit": 8,
		"onBasePercentage": 0.2796208530805687,
		"onBasePlusSlugging": 0.7318821596132321,
		"plateAppearances": 641,
		"runsBattedIn": 55,
		"runsScored": 59,
		"sacrificeBunts": 8,
		"sacrificeFlies": 9,
		"sluggingPercentage": 0.45226130653266333,
		"stolenBases": 2,
		"strikeouts": 62,
		"team": null,
		"teamName": null,
		"totalBases": 270,
		"triplesHit": 44
	},
	"id": "ce0e57a7-89f5-41ea-80f9-6e649dd54089",
	"name": "Yong Wright",
	"seasons": {
		"1": {
			"appearances": 62,
			"atBats": 237,
			"basesOnBalls": 12,
			"battingAverage": 0.24050632911392406,
			"caughtStealing": 1,
			"doublesHit": 6,
			"groundIntoDoublePlays": 1,
			"hits": 57,
			"homeRunsHit": 2,
			"onBasePercentage": 0.2749003984063745,
			"onBasePlusSlugging": 0.7179383730899187,
			"plateAppearances": 253,
			"runsBattedIn": 19,
			"runsScored": 16,
			"sacrificeBunts": 2,
			"sacrificeFlies": 2,
			"sluggingPercentage": 0.4430379746835443,
			"stolenBases": 2,
			"strikeouts": 29,
			"team": "57ec08cc-0411-4643-b304-0e80dbc15ac7",
			"teamName": "Mexico City Wild Wings",
			"totalBases": 105,
			"triplesHit": 18
		},
		"2": {
			"appearances": 98,
			"atBats": 360,
			"basesOnBalls": 15,
			"battingAverage": 0.25833333333333336,
			"caughtStealing": 5,
			"doublesHit": 2,
			"groundIntoDoublePlays": 1,
			"hits": 93,
			"homeRunsHit": 6,
			"onBasePercentage": 0.28272251308900526,
			"onBasePlusSlugging": 0.7410558464223386,
			"plateAppearances": 388,
			"runsBattedIn": 36,
			"runsScored": 43,
			"sacrificeBunts": 6,
			"sacrificeFlies": 7,
			"sluggingPercentage": 0.4583333333333333,
			"stolenBases": 0,
			"strikeouts": 33,
			"team": "57ec08cc-0411-4643-b304-0e80dbc15ac7",
			"teamName": "Mexico City Wild Wings",
			"totalBases": 165,
			"triplesHit": 26
		}
	},
	"slug": "yong-wright",
	"postseasons": {}
}
