{
	"careerPostseason": {
		"appearances": 0,
		"atBats": 0,
		"basesOnBalls": 0,
		"battingAverage": 0,
		"caughtStealing": 0,
		"doublesHit": 0,
		"groundIntoDoublePlays": 0,
		"hits": 0,
		"homeRunsHit": 0,
		"onBasePercentage": 0,
		"onBasePlusSlugging": 0,
		"plateAppearances": 0,
		"runsBattedIn": 0,
		"runsScored": 0,
		"sacrificeBunts": 0,
		"sacrificeFlies": 0,
		"sluggingPercentage": 0,
		"stolenBases": 0,
		"strikeouts": 0,
		"team": null,
		"teamName": null,
		"totalBases": 0,
		"triplesHit": 0
	},
	"careerSeason": {
		"appearances": 35,
		"atBats": 153,
		"basesOnBalls": 5,
		"battingAverage": 0.4117647058823529,
		"caughtStealing": 0,
		"doublesHit": 5,
		"groundIntoDoublePlays": 2,
		"hits": 63,
		"homeRunsHit": 2,
		"onBasePercentage": 0.425,
		"onBasePlusSlugging": 0.9870915032679739,
		"plateAppearances": 162,
		"runsBattedIn": 25,
		"runsScored": 26,
		"sacrificeBunts": 2,
		"sacrificeFlies": 2,
		"sluggingPercentage": 0.5620915032679739,
		"stolenBases": 3,
		"strikeouts": 17,
		"team": null,
		"teamName": null,
		"totalBases": 86,
		"triplesHit": 6
	},
	"id": "c83a13f6-ee66-4b1c-9747-faa67395a6f1",
	"name": "Zi Delacruz",
	"seasons": {
		"1": {
			"appearances": 35,
			"atBats": 153,
			"basesOnBalls": 5,
			"battingAverage": 0.4117647058823529,
			"caughtStealing": 0,
			"doublesHit": 5,
			"groundIntoDoublePlays": 2,
			"hits": 63,
			"homeRunsHit": 2,
			"onBasePercentage": 0.425,
			"onBasePlusSlugging": 0.9870915032679739,
			"plateAppearances": 162,
			"runsBattedIn": 25,
			"runsScored": 26,
			"sacrificeBunts": 2,
			"sacrificeFlies": 2,
			"sluggingPercentage": 0.5620915032679739,
			"stolenBases": 3,
			"strikeouts": 17,
			"team": "b024e975-1c4a-4575-8936-a3754a08806a",
			"teamName": "Dallas Steaks",
			"totalBases": 86,
			"triplesHit": 6
		}
	},
	"slug": "zi-delacruz",
	"postseasons": {}
}
